ampoul3-0.3.0.dist-info/DESCRIPTION.rst
ampoul3-0.3.0.dist-info/METADATA
ampoul3-0.3.0.dist-info/RECORD
ampoul3-0.3.0.dist-info/WHEEL
ampoul3-0.3.0.dist-info/metadata.json
ampoul3-0.3.0.dist-info/top_level.txt
ampoule/__init__.py
ampoule/child.py
ampoule/commands.py
ampoule/iampoule.py
ampoule/main.py
ampoule/pool.py
ampoule/rpool.py
ampoule/service.py
ampoule/util.py
ampoule/__pycache__/__init__.cpython-36.opt-1.pyc
ampoule/__pycache__/child.cpython-36.opt-1.pyc
ampoule/__pycache__/commands.cpython-36.opt-1.pyc
ampoule/__pycache__/iampoule.cpython-36.opt-1.pyc
ampoule/__pycache__/main.cpython-36.opt-1.pyc
ampoule/__pycache__/pool.cpython-36.opt-1.pyc
ampoule/__pycache__/rpool.cpython-36.opt-1.pyc
ampoule/__pycache__/service.cpython-36.opt-1.pyc
ampoule/__pycache__/util.cpython-36.opt-1.pyc
ampoule/test/__init__.py
ampoule/test/test_process.py
ampoule/test/test_proxy.py
ampoule/test/__pycache__/__init__.cpython-36.opt-1.pyc
ampoule/test/__pycache__/test_process.cpython-36.opt-1.pyc
ampoule/test/__pycache__/test_proxy.cpython-36.opt-1.pyc
twisted/plugins/ampoule_plugin.py
twisted/plugins/__pycache__/ampoule_plugin.cpython-36.opt-1.pyc
