Metadata-Version: 2.0
Name: ampoul3
Version: 0.3.0
Summary: A process pool implementation in Twisted Matrix and AMP
Home-page: https://launchpad.net/ampoule
Author: Glyph Lefkowitz
Author-email: glyph@twistedmatrix.com
License: MIT License
Platform: UNKNOWN
Classifier: Development Status :: 4 - Beta
Classifier: Environment :: Console
Classifier: Intended Audience :: Developers
Classifier: License :: OSI Approved :: MIT License
Classifier: Natural Language :: English
Classifier: Programming Language :: Python
Classifier: Topic :: System
Requires-Dist: Twisted (>=17[tls])
